LICENSE
hypertag/__init__.py
hypertag/__main__.py
hypertag/daemon.py
hypertag/graph.py
hypertag/hypertag.py
hypertag/persistor.py
hypertag/tokenizer.py
hypertag/utils.py
hypertag/vectorizer.py
hypertag/webapi.py
hypertag-0.6.3.3.1.dist-info/LICENSE
hypertag-0.6.3.3.1.dist-info/WHEEL
hypertag-0.6.3.3.1.dist-info/METADATA
hypertag-0.6.3.3.1.dist-info/RECORD
