Metadata-Version: 2.1
Name: hypertag
Version: 0.6.3.3.1
Summary: File organization made for humans
Home-page: https://github.com/SeanPedersen/HyperTag
License: MIT
Keywords: tag,tagging,file-system,file,organization,search,semantic,text,image,pdf
Author: Sean
Author-email: sean.pedersen96@gmail.com
Requires-Python: >=3.6.2,<4.0.0
Classifier: Environment :: Console
Classifier: License :: OSI Approved :: MIT License
Classifier: Programming Language :: Python :: 3
Classifier: Programming Language :: Python :: 3.7
Classifier: Programming Language :: Python :: 3.8
Classifier: Programming Language :: Python :: 3.9
Classifier: Programming Language :: Python :: 3.10
Classifier: Programming Language :: Python :: 3.11
Requires-Dist: Pillow (>=8.1.0,<9.0.0)
Requires-Dist: PyPDF2 (>=1.26.0,<2.0.0)
Requires-Dist: cairocffi (>=1.2.0,<2.0.0)
Requires-Dist: filetype (>=1.0.7,<2.0.0)
Requires-Dist: fire (>=0.3.1,<0.4.0)
Requires-Dist: ftfy (>=5.8,<6.0)
Requires-Dist: fuzzywuzzy[speedup] (>=0.18.0,<0.19.0)
Requires-Dist: hnswlib (>=0.4.0,<0.5.0)
Requires-Dist: pywebcopy (>=6.3.0,<7.0.0)
Requires-Dist: rpyc (>=5.0.0,<6.0.0)
Requires-Dist: sentence-transformers (>=0.4.1,<0.5.0)
Requires-Dist: textract (>=1.6.3,<2.0.0)
Requires-Dist: torchvision (>=0.8.2,<0.9.0)
Requires-Dist: tqdm (>=4.55.0,<5.0.0)
Requires-Dist: watchdog (>=1.0.2,<2.0.0)
Requires-Dist: wordninja (>=2.0.0,<3.0.0)
Project-URL: Repository, https://github.com/SeanPedersen/HyperTag
